<?xml version="1.0" encoding="utf-8" ?>
<dwsync>
<file name="style.css" local="130222319832625626" remote="130222319830000000" testing="0" />
<file name="style.responsive.css" local="130222319831825087" remote="130222319830000000" testing="0" />
<file name="jquery.js" local="130222319831354780" remote="130222319830000000" testing="0" />
<file name="script.js" local="130222319831995200" remote="130222319830000000" testing="0" />
<file name="script.responsive.js" local="130222319831414826" remote="130222319830000000" testing="0" />
<file name="style.css" local="130222319832625626" remote="130222319830000000" testing="0" />
<file name="style.responsive.css" local="130222319831825087" remote="130222319830000000" testing="0" />
<file name="jquery.js" local="130222319831354780" remote="130222319830000000" testing="0" />
<file name="script.js" local="130222319831995200" remote="130222319830000000" testing="0" />
<file name="script.responsive.js" local="130222319831414826" remote="130222319830000000" testing="0" />
<file name="style.css" local="130222319832625620" remote="130222319830000000" testing="0" />
<file name="style.responsive.css" local="130222319831825080" remote="130222319830000000" testing="0" />
<file name="jquery.js" local="130222319831354780" remote="130222319830000000" testing="0" />
<file name="script.js" local="130222319831995200" remote="130222319830000000" testing="0" />
<file name="script.responsive.js" local="130222319831414820" remote="130222319830000000" testing="0" />
<file name="main.php" local="130222386373240030" remote="130222386370000000" testing="0" />
<file name="banner.php" local="130222345560787187" remote="130222345560000000" testing="0" />
<file name="style.css" local="130222319832625620" remote="130222319830000000" testing="0" />
<file name="style.responsive.css" local="130222319831825080" remote="130222319830000000" testing="0" />
<file name="jquery.js" local="130222319831354780" remote="130222319830000000" testing="0" />
<file name="script.js" local="130222319831995200" remote="130222319830000000" testing="0" />
<file name="script.responsive.js" local="130222319831414820" remote="130222319830000000" testing="0" />
<file name="main.php" local="130222386373240030" remote="130222386370000000" testing="0" />
<file name="style.css" local="130222319832625620" remote="130222319830000000" testing="0" />
<file name="style.responsive.css" local="130222319831825080" remote="130222319830000000" testing="0" />
<file name="jquery.js" local="130222319831354780" remote="130222319830000000" testing="0" />
<file name="script.js" local="130222319831995200" remote="130222319830000000" testing="0" />
<file name="script.responsive.js" local="130222319831414820" remote="130222319830000000" testing="0" />
<file name="main.php" local="130222386373240030" remote="130222386370000000" testing="0" />
</dwsync>